<?xml version="1.1" encoding="UTF-8"?>

<channel name="xfce4-panel" version="1.0">
  <property name="configver" type="int" value="2"/>
  <property name="panels" type="array">
    <value type="int" value="1"/>
    <property name="dark-mode" type="bool" value="true"/>
    <property name="panel-1" type="empty">
      <property name="position" type="string" value="p=6;x=0;y=0"/>
      <property name="length" type="uint" value="100"/>
      <property name="position-locked" type="bool" value="true"/>
      <property name="icon-size" type="uint" value="0"/>
      <property name="size" type="uint" value="36"/>
      <property name="plugin-ids" type="array">
        <value type="int" value="14"/>
        <value type="int" value="28"/>
        <value type="int" value="23"/>
        <value type="int" value="4"/>
        <value type="int" value="5"/>
        <value type="int" value="26"/>
        <value type="int" value="25"/>
        <value type="int" value="24"/>
        <value type="int" value="27"/>
        <value type="int" value="2"/>
        <value type="int" value="3"/>
        <value type="int" value="37"/>
        <value type="int" value="35"/>
        <value type="int" value="11"/>
        <value type="int" value="10"/>
        <value type="int" value="33"/>
        <value type="int" value="34"/>
        <value type="int" value="6"/>
        <value type="int" value="8"/>
        <value type="int" value="9"/>
        <value type="int" value="12"/>
        <value type="int" value="13"/>
        <value type="int" value="38"/>
        <value type="int" value="7"/>
      </property>
      <property name="enable-struts" type="bool" value="true"/>
      <property name="leave-opacity" type="uint" value="72"/>
      <property name="enter-opacity" type="uint" value="72"/>
      <property name="background-style" type="uint" value="0"/>
    </property>
  </property>
  <property name="plugins" type="empty">
    <property name="plugin-2" type="string" value="tasklist">
      <property name="grouping" type="uint" value="1"/>
      <property name="flat-buttons" type="bool" value="false"/>
      <property name="show-handle" type="bool" value="false"/>
    </property>
    <property name="plugin-3" type="string" value="separator">
      <property name="expand" type="bool" value="true"/>
      <property name="style" type="uint" value="0"/>
    </property>
    <property name="plugin-4" type="string" value="pager">
      <property name="rows" type="uint" value="1"/>
      <property name="miniature-view" type="bool" value="false"/>
      <property name="numbering" type="bool" value="false"/>
      <property name="wrap-workspaces" type="bool" value="true"/>
    </property>
    <property name="plugin-5" type="string" value="separator">
      <property name="style" type="uint" value="0"/>
    </property>
    <property name="plugin-6" type="string" value="systray">
      <property name="square-icons" type="bool" value="true"/>
      <property name="known-legacy-items" type="array">
        <value type="string" value="wi-fi network connection “smartrg-c567-5g” active: smartrg-c567-5g (59%)"/>
        <value type="string" value="wi-fi network connection “smartrg-c567-5g” active: smartrg-c567-5g (58%)"/>
        <value type="string" value="wi-fi network connection “smartrg-c567-5g” active: smartrg-c567-5g (67%)"/>
        <value type="string" value="wi-fi network connection “smartrg-c567-5g” active: smartrg-c567-5g (65%)"/>
        <value type="string" value="wi-fi network connection “smartrg-c567-5g” active: smartrg-c567-5g (66%)"/>
        <value type="string" value="wi-fi network connection “smartrg-c567-5g” active: smartrg-c567-5g (60%)"/>
        <value type="string" value="wi-fi network connection “smartrg-c567-5g” active: smartrg-c567-5g (63%)"/>
        <value type="string" value="wi-fi network connection “smartrg-c567-5g” active: smartrg-c567-5g (61%)"/>
        <value type="string" value="wi-fi network connection “smartrg-c567-5g” active: smartrg-c567-5g (56%)"/>
        <value type="string" value="wi-fi network connection “smartrg-c567-5g” active: smartrg-c567-5g (57%)"/>
        <value type="string" value="wi-fi network connection “crisval_6g” active: crisval_6g (56%)"/>
        <value type="string" value="no network connection"/>
        <value type="string" value="wi-fi network connection “bell879” active: bell879 (68%)"/>
        <value type="string" value="clipman"/>
        <value type="string" value="notes"/>
        <value type="string" value="configuring wi-fi network connection “bell879”…"/>
        <value type="string" value="wi-fi network connection “bell879” active: bell879 (65%)"/>
        <value type="string" value="blueberry-tray.py"/>
        <value type="string" value="nemo"/>
        <value type="string" value="wi-fi network connection “bell879” active: bell879 (67%)"/>
        <value type="string" value="wi-fi network connection “bell879” active: bell879 (56%)"/>
        <value type="string" value="wi-fi network connection “bell879” active: bell879 (61%)"/>
        <value type="string" value="wi-fi network connection “bell879” active: bell879 (71%)"/>
        <value type="string" value="wi-fi network connection “bell879” active: bell879 (69%)"/>
        <value type="string" value="wi-fi network connection “bell879” active: bell879 (62%)"/>
        <value type="string" value="blueman"/>
        <value type="string" value="wi-fi network connection “bell879” active: bell879 (70%)"/>
        <value type="string" value="wi-fi network connection “bell879” active: bell879 (73%)"/>
        <value type="string" value="wi-fi network connection “bell879” active: bell879 (72%)"/>
        <value type="string" value="wi-fi network connection “bell879” active: bell879 (74%)"/>
        <value type="string" value="pamac-tray"/>
        <value type="string" value="wi-fi network connection “bell879” active: bell879 (60%)"/>
        <value type="string" value="wi-fi network connection “bell879” active: bell879 (63%)"/>
        <value type="string" value="wi-fi network connection “bell879” active: bell879 (75%)"/>
        <value type="string" value="requesting a wi-fi network address for “bell879”…"/>
        <value type="string" value="ethernet network connection “wired connection 1” active"/>
        <value type="string" value="firewall-applet"/>
        <value type="string" value=""/>
      </property>
      <property name="known-items" type="array">
        <value type="string" value="tao application"/>
        <value type="string" value="chrome_status_icon_1"/>
        <value type="string" value="blueman"/>
        <value type="string" value="nm-applet"/>
        <value type="string" value="firewall-applet"/>
      </property>
    </property>
    <property name="plugin-8" type="string" value="pulseaudio">
      <property name="enable-keyboard-shortcuts" type="bool" value="true"/>
      <property name="show-notifications" type="bool" value="true"/>
      <property name="known-players" type="string" value="firefox"/>
    </property>
    <property name="plugin-9" type="string" value="power-manager-plugin"/>
    <property name="plugin-10" type="string" value="notification-plugin"/>
    <property name="plugin-11" type="string" value="separator">
      <property name="style" type="uint" value="0"/>
    </property>
    <property name="plugin-12" type="string" value="clock">
      <property name="digital-time-font" type="string" value="Sans 10"/>
      <property name="digital-time-format" type="string" value="%I:%M %p"/>
      <property name="digital-layout" type="uint" value="3"/>
    </property>
    <property name="plugin-13" type="string" value="separator">
      <property name="style" type="uint" value="0"/>
    </property>
    <property name="plugin-14" type="string" value="separator">
      <property name="style" type="uint" value="0"/>
      <property name="expand" type="bool" value="false"/>
    </property>
    <property name="plugin-23" type="string" value="separator">
      <property name="style" type="uint" value="0"/>
    </property>
    <property name="plugin-24" type="string" value="launcher">
      <property name="items" type="array">
        <value type="string" value="17329953093.desktop"/>
      </property>
    </property>
    <property name="plugin-25" type="string" value="launcher">
      <property name="items" type="array">
        <value type="string" value="17329952992.desktop"/>
      </property>
    </property>
    <property name="plugin-26" type="string" value="launcher">
      <property name="items" type="array">
        <value type="string" value="17329952831.desktop"/>
      </property>
    </property>
    <property name="plugin-27" type="string" value="separator">
      <property name="style" type="uint" value="2"/>
    </property>
    <property name="plugin-28" type="string" value="applicationsmenu">
      <property name="button-icon" type="string" value="start-here-archlinux"/>
    </property>
    <property name="plugin-34" type="string" value="fsguard"/>
    <property name="plugin-35" type="string" value="netload"/>
    <property name="plugin-37" type="string" value="weather">
      <property name="location" type="empty">
        <property name="name" type="string" value="Pickering, Durham Region"/>
        <property name="latitude" type="string" value="43.835765"/>
        <property name="longitude" type="string" value="-79.090576"/>
      </property>
      <property name="msl" type="int" value="88"/>
      <property name="timezone" type="string" value="America/Toronto"/>
      <property name="offset" type="string" value="-04:00"/>
      <property name="cache-max-age" type="int" value="172800"/>
      <property name="power-saving" type="bool" value="true"/>
      <property name="units" type="empty">
        <property name="temperature" type="int" value="0"/>
        <property name="pressure" type="int" value="0"/>
        <property name="windspeed" type="int" value="0"/>
        <property name="precipitation" type="int" value="0"/>
        <property name="altitude" type="int" value="0"/>
        <property name="apparent-temperature" type="int" value="2"/>
      </property>
      <property name="round" type="bool" value="true"/>
      <property name="single-row" type="bool" value="true"/>
      <property name="tooltip-style" type="int" value="1"/>
      <property name="forecast" type="empty">
        <property name="layout" type="int" value="1"/>
        <property name="days" type="int" value="5"/>
      </property>
      <property name="theme-dir" type="string" value="/usr/share/xfce4/weather/icons/liquid"/>
      <property name="scrollbox" type="empty">
        <property name="show" type="bool" value="true"/>
        <property name="animate" type="bool" value="true"/>
        <property name="lines" type="int" value="1"/>
        <property name="color" type="string" value="rgba(0,0,0,0)"/>
        <property name="use-color" type="bool" value="false"/>
      </property>
      <property name="labels" type="empty">
        <property name="label0" type="int" value="3"/>
        <property name="label1" type="int" value="11"/>
      </property>
    </property>
    <property name="plugin-38" type="string" value="separator"/>
    <property name="plugin-33" type="string" value="xfce4-notes-plugin"/>
    <property name="notes" type="empty">
      <property name="global" type="empty">
        <property name="version" type="string" value="1.12.0"/>
      </property>
    </property>
    <property name="plugin-7" type="string" value="launcher">
      <property name="items" type="array">
        <value type="string" value="17513909261.desktop"/>
      </property>
    </property>
  </property>
</channel>
